{"type":"object","properties":{"items":{"type":"array","items":{"type":"object","properties":{"name":{"type":"string"},"location":{"type":"string"},"supervisorId":{"type":"string"},"id":{"type":"string"},"createdAt":{"format":"date-time","type":"string"},"updatedAt":{"format":"date-time","type":"string"},"deviceCount":{"type":"number"},"supervisor":{"type":"object","properties":{"name":{"type":"string"},"username":{"type":"string","description":"Username has to be 4 letters or more"},"userTypeId":{"type":"string"},"id":{"type":"string"}},"required":["name","username","userTypeId","id"],"x-readme-ref-name":"UserDto"},"status":{"type":"string","enum":["Available","In Use","Under Maintenance"]}},"required":["name","location","supervisorId","id","createdAt","updatedAt","deviceCount","supervisor","status"],"x-readme-ref-name":"LabListDto"}},"total":{"type":"number"}},"required":["items","total"],"x-readme-ref-name":"LabPagedDto"}